interpixpy/__init__.py
interpixpy/sdk.py
interpixpy/config/__init__.py
interpixpy/config/config.py
interpixpy/config/request_options.py
interpixpy/core/__init__.py
interpixpy/core/auth_manager.py
interpixpy/core/pixpy_base.py
interpixpy/http/__init__.py
interpixpy/http/http_client.py
interpixpy/resources/__init__.py
interpixpy/resources/cob.py
interpixpy/resources/cobv.py
interpixpy/resources/location.py
interpixpy/resources/pix.py
interpixpy/resources/webhook.py
inter_pixpy-0.0.7.dist-info/LICENSE
inter_pixpy-0.0.7.dist-info/METADATA
inter_pixpy-0.0.7.dist-info/WHEEL
inter_pixpy-0.0.7.dist-info/top_level.txt
inter_pixpy-0.0.7.dist-info/RECORD
