Metadata-Version: 2.1
Name: inter-pixpy
Version: 0.0.7
Summary: A Python package to interact with the Banco Inter's Pix API
Home-page: https://github.com/samueljansem/interpixpy
Author: Samuel Jansem
Author-email: samuel.jansem@gmail.com
License: MIT
Project-URL: Source Code, https://github.com/samueljansem/interpixpy
Project-URL: Issues, https://github.com/samueljansem/interpixpy/issues
Keywords: pix,inter,bank,api,python,sdk
Platform: UNKNOWN
Classifier: Programming Language :: Python :: 3
Classifier: License :: OSI Approved :: MIT License
Classifier: Operating System :: OS Independent
Requires-Python: >=3
Requires-Dist: requests
